LatinDeckCreator/__init__.py
LatinDeckCreator/deckwriter.py
LatinDeckCreator/filehandler.py
LatinDeckCreator/jsonhandler.py
LatinDeckCreator-0.0.5.dist-info/LICENSE
LatinDeckCreator-0.0.5.dist-info/METADATA
LatinDeckCreator-0.0.5.dist-info/WHEEL
LatinDeckCreator-0.0.5.dist-info/top_level.txt
LatinDeckCreator-0.0.5.dist-info/RECORD
